{"packageId":"G68","sortKey":"F","description":"G68 - Asset-Liab Reclass JE","parentPackageId":"4","packageType":"glsUs","elimination":null,"elimSelects":[{"elimID":"68","pass":1,"subSeq":1,"fieldName":"Co","fieldNbr":1,"incExcl":"I","oper":"EQ","fromVal":"2008","thruVal":"","glsu":"y","dateTimeStamp":"2024-06-13T13:46:37.0933333"},{"elimID":"68","pass":1,"subSeq":1,"fieldName":"TP","fieldNbr":2,"incExcl":"I","oper":"EQ","fromVal":"3030","thruVal":"","glsu":"y","dateTimeStamp":"2024-06-13T13:46:37.0933333"},{"elimID":"68","pass":2,"subSeq":1,"fieldName":"Co","fieldNbr":1,"incExcl":"I","oper":"EQ","fromVal":"3030","thruVal":"","glsu":"y","dateTimeStamp":"2024-06-13T13:46:37.0933333"},{"elimID":"68","pass":2,"subSeq":1,"fieldName":"TP","fieldNbr":2,"incExcl":"I","oper":"EQ","fromVal":"2008","thruVal":"","glsu":"y","dateTimeStamp":"2024-06-13T13:46:37.0933333"}],"sqlCommand":[{"table_ID":"SQL-G68","id":"105","descr":"insert into TransX (KeyID,Co,GL,Amt1,Flex8) (select KeyID,Co,GL,round(sum(Amt1),2),'pass1' from TransX where KeyID = '[batchID]' group by KeyID,Co,GL)"},{"table_ID":"SQL-G68","id":"106","descr":"delete from TransX where KeyID = '[batchID]' and Flex8 is NULL"},{"table_ID":"SQL-G68","id":"107","descr":"delete from TransX where KeyID = '[batchID]' and Amt1 = 0"},{"table_ID":"SQL-G68","id":"111","descr":"update TransX set Flex2 = m.Mapkey, Flex3 = x.Field1 from TransX t inner join mapkeyranges m on t.GL >= m.fromGL and t.GL <=m.thruGL inner join Misc_Tables x on m.MapKey = x.Descr and x.Table_ID = 'G68' and x.ID = 'Mapkeys' where keyID = '[batchID]' and x.Field3 = '[version]'"},{"table_ID":"SQL-G68","id":"112","descr":"update TransX set Flex4 = m.Name from TransX t inner join Mapkeys m on t.Flex2 = m.Mapkey where keyID = '[batchID]'"},{"table_ID":"SQL-G68","id":"121","descr":"update t set Amt2 = x.Tot from TransX t inner join (Select Flex3,sum(Amt1) as Tot from TransX where KeyID = '[batchID]' group by Flex3) x   on t.Flex3 = x.Flex3 where t.KeyID = '[batchID]' and '[version]' = 'UG'"},{"table_ID":"SQL-G68","id":"122","descr":"update t set Amt2 = x.Tot from TransX t inner join (Select Co,Flex3,sum(Amt1) as Tot from TransX where KeyID = '[batchID]' group by Co,Flex3) x   on t.Co = x.Co and t.Flex3 = x.Flex3 where t.KeyID = '[batchID]' and t.Co > '2008' and t.Co < '4500'  and '[version]' = 'US'"},{"table_ID":"SQL-G68","id":"123","descr":"update t set Amt2 = x.Tot from TransX t inner join (Select Flex3,sum(Amt1) as Tot from TransX where KeyID = '[batchID]'  and (Co <= '2008' or Co >= '4500') group by Flex3) x on t.Flex3 = x.Flex3 where t.KeyID = '[batchID]' and (t.Co <= '2008' or t.Co >= '4500') and '[version]' = 'US'"},{"table_ID":"SQL-G68","id":"131","descr":"insert into TransX (KeyID,Co,GL,Flex2,Flex3,Flex4,Amt1,Amt2) (select KeyID + '-data2',Co,GL,Flex2,Flex3,Flex4,Amt1,Amt2 from TransX where KeyID = '[batchID]')"},{"table_ID":"SQL-G68","id":"141","descr":"insert into TransX (KeyID,Co,GL,Flex2,Flex3,Flex5,Amt1) (select KeyID,'2999' as Co,GL,Flex2,GL,'pass1',round(-sum(Amt1),2) as Amt1 from TransX where KeyID = '[batchID]' and GL < '2000000' and Amt2 < 0 and '[version]' = 'UG' group by KeyID,GL,Flex2)"},{"table_ID":"SQL-G68","id":"142","descr":"insert into TransX (KeyID,Co,GL,Flex2,Flex3,Flex5,Amt1) (select KeyID,'2999' as Co,GL,Flex2,GL,'pass1',round(-sum(Amt1),2) as Amt1 from TransX where KeyID = '[batchID]' and GL >= '2000000' and Amt2 > 0 and Flex5 is NULL and '[version]' = 'UG' group by KeyID,GL,Flex2)"},{"table_ID":"SQL-G68","id":"144","descr":"insert into TransX (KeyID,Co,GL,Flex2,Flex3,Flex5,Amt1) (select KeyID,Co,GL,Flex2,GL,'pass1',-Amt1 from TransX where KeyID = '[batchID]' and GL < '2000000' and Amt2 < 0 and '[version]' = 'US')"},{"table_ID":"SQL-G68","id":"145","descr":"insert into TransX (KeyID,Co,GL,Flex2,Flex3,Flex5,Amt1) (select KeyID,Co,GL,Flex2,GL,'pass1',-Amt1 from TransX where KeyID = '[batchID]' and GL >= '2000000' and Amt2 > 0 and Flex5 is NULL and '[version]' = 'US')"},{"table_ID":"SQL-G68","id":"146","descr":"delete from TransX where KeyID = '[batchID]' and Flex5 is NULL"},{"table_ID":"SQL-G68","id":"148","descr":"insert into TransX (KeyID,Co,GL,Flex2,Flex3,Amt1) (select t.KeyID,t.Co,m.Field1,t.Flex2,Flex3,-Amt1 from TransX t inner join Misc_Tables m on m.Descr = t.GL and m.Table_ID = 'G68' and m.ID = 'GL offsets' where KeyID = '[batchID]')"},{"table_ID":"SQL-G68","id":"201","descr":"Update TransX set GL = '2630000' where KeyID = '[batchID]' and GL = '2620007' and '[version]' = 'US'"},{"table_ID":"SQL-G68","id":"202","descr":"Update TransX set GL = '1730000' where KeyID = '[batchID]' and GL = '1720007' and '[version]' = 'US'"},{"table_ID":"SQL-G68","id":"302","descr":"Update TransX set Txt = substring('Asset-Liab Reclass JE for [Yr]-[Mo] ' + Flex3,1,50),Flex1 = '',PC = '5500000000' where KeyID = '[batchID]'"},{"table_ID":"SQL-G68","id":"303","descr":"Update x set x.GLdesc = y.Descr from TransX x inner join COA y on x.GL = y.GL where KeyID like '[batchID]%'"},{"table_ID":"SQL-G68","id":"304","descr":"Update TransX set PK = (case when Amt1 > 0 then '40' else '50' end) where KeyID = '[batchID]'"},{"table_ID":"SQL-G68","id":"305","descr":"Update TransX set TTY = '705' where KeyID = '[batchID]'"},{"table_ID":"SQL-G68","id":"306","descr":"Update TransX set TTY = '990' where KeyID = '[batchID]' and GL like '%9998'"},{"table_ID":"SQL-G68","id":"307","descr":"Update TransX set TTY = '' where KeyID = '[batchID]' and GL = '2630000'"}],"sqlSelect":[{"table_ID":"SQLselect","id":"G68","descr":"insert into TransX (KeyID,Co,GL,Amt1) values ('[batchID]',"}]}